scot/__init__.py
scot/backend_builtin.py
scot/backend_sklearn.py
scot/backendmanager.py
scot/config.py
scot/connectivity.py
scot/connectivity_statistics.py
scot/csp.py
scot/datatools.py
scot/matfiles.py
scot/ooapi.py
scot/parallel.py
scot/pca.py
scot/plainica.py
scot/plotting.py
scot/scot.ini
scot/utils.py
scot/var.py
scot/varbase.py
scot/varica.py
scot/xvschema.py
scot/eegtopo/__init__.py
scot/eegtopo/eegpos3d.py
scot/eegtopo/geo_euclidean.py
scot/eegtopo/geo_spherical.py
scot/eegtopo/projections.py
scot/eegtopo/tools.py
scot/eegtopo/topoplot.py
scot/eegtopo/warp_layout.py
scot/external/__init__.py
scot/external/infomax_.py
scot-0.2.1.dist-info/DESCRIPTION.rst
scot-0.2.1.dist-info/METADATA
scot-0.2.1.dist-info/RECORD
scot-0.2.1.dist-info/WHEEL
scot-0.2.1.dist-info/metadata.json
scot-0.2.1.dist-info/top_level.txt
