Metadata-Version: 2.0
Name: scot
Version: 0.2.1
Summary: EEG/MEG Source Connectivity Toolbox
Home-page: https://github.com/scot-dev/scot
Author: SCoT Development Team
Author-email: scotdev@googlegroups.com
License: MIT
